ipy_agent/__init__.py
ipy_agent/attrdict.py
ipy_agent/default_preprompt.txt
ipy_agent/dictation.py
ipy_agent/get_text.py
ipy_agent/get_webdriver.py
ipy_agent/google_search.py
ipy_agent/init.py
ipy_agent/init_shell.py
ipy_agent/ipy_agent.py
ipy_agent/llm_client.py
ipy_agent/main.py
ipy_agent/msg_collector.py
ipy_agent/retrieval.py
ipy_agent/tools.py
ipy_agent/utils.py
ipy_agent/voice.py
ipy_agent-0.0.8.dist-info/LICENSE
ipy_agent-0.0.8.dist-info/METADATA
ipy_agent-0.0.8.dist-info/WHEEL
ipy_agent-0.0.8.dist-info/entry_points.txt
ipy_agent-0.0.8.dist-info/top_level.txt
ipy_agent-0.0.8.dist-info/RECORD
