Metadata-Version: 2.1
Name: ipy_agent
Version: 0.0.8
Summary: An AI assistant designed to be integrated in an IPython shell.
Home-page: https://github.com/B4PT0R/ipy_agent
Author: Baptiste Ferrand
Author-email: bferrand.maths@gmail.com
Classifier: Programming Language :: Python :: 3
Classifier: License :: OSI Approved :: MIT License
Classifier: Operating System :: OS Independent
Requires-Python: >=3.9
License-File: LICENSE
Requires-Dist: ipython
Requires-Dist: PyPDF2
Requires-Dist: beautifulsoup4
Requires-Dist: python-docx
Requires-Dist: get-gecko-driver
Requires-Dist: google-api-python-client
Requires-Dist: litellm
Requires-Dist: numpy
Requires-Dist: odfpy
Requires-Dist: openai
Requires-Dist: pydub
Requires-Dist: pynput
Requires-Dist: requests
Requires-Dist: selenium
Requires-Dist: sounddevice
Requires-Dist: tiktoken
Requires-Dist: python-dotenv
